foxkit/__init__.py
foxkit/file/__init__.py
foxkit/file/excel.py
foxkit/source/__init__.py
foxkit/source/headers.py
foxkit/utils/__init__.py
foxkit/utils/config.py
foxkit-0.0.6.dist-info/METADATA
foxkit-0.0.6.dist-info/WHEEL
foxkit-0.0.6.dist-info/top_level.txt
foxkit-0.0.6.dist-info/RECORD
