Metadata-Version: 2.4
Name: foxkit
Version: 0.0.6
Summary: 工具盒子
Home-page: https://github.com/
Author: MR.AH
Author-email: zhangzhonghui1001@gmail.com
Classifier: Programming Language :: Python :: 3
Classifier: License :: OSI Approved :: MIT License
Classifier: Operating System :: OS Independent
Requires-Python: >=3
Requires-Dist: openpyxl
Requires-Dist: pillow
Requires-Dist: requests
Requires-Dist: tqdm
Requires-Dist: typing_extensions
Requires-Dist: urllib3
Dynamic: author
Dynamic: author-email
Dynamic: classifier
Dynamic: description
Dynamic: description-content-type
Dynamic: home-page
Dynamic: requires-dist
Dynamic: requires-python
Dynamic: summary
